bangumi/__init__.py
bangumi/api_endpoints.py
bangumi/client.py
bangumi/collection.py
bangumi/entity.py
bangumi/enum.py
bangumi/subject.py
bangumi/timeline.py
bilibili/__init__.py
bilibili/api_endpoints.py
bilibili/cilent.py
bilibili/entity.py
bilibili/favlist.py
cnblog/__init__.py
cnblog/api_endpoints.py
cnblog/blog_post.py
cnblog/bookmark.py
cnblog/client.py
cnblog/user.py
demo/__init__.py
demo/api_endpoints.py
demo/cilent.py
demo/entity.py
export_to_obsidian.py
qireader/__init__.py
qireader/api_endpoints.py
qireader/cilent.py
qireader/getext.py
qireader/models.py
qireader/readlatter.py
utils/__init__.py
utils/file_utils.py
utils/md_utils.py
utils/template.py
v2ex/__init__.py
v2ex/api_endpoints.py
v2ex/cilent.py
v2ex/entity.py
v2ex/mytopic.py
v2ex/topic.py
weibo/__init__.py
weibo/api_endpoints.py
weibo/cilent.py
weibo/entity.py
weibo/like.py
weibo/post.py
zhihu/__init__.py
zhihu/api_endpoints.py
zhihu/cilent.py
zhihu/collection.py
zhihu/entity.py
export_to_obsidian-0.3.25.2.dist-info/LICENCE
export_to_obsidian-0.3.25.2.dist-info/METADATA
export_to_obsidian-0.3.25.2.dist-info/WHEEL
export_to_obsidian-0.3.25.2.dist-info/entry_points.txt
export_to_obsidian-0.3.25.2.dist-info/RECORD
