Metadata-Version: 2.3
Name: export_to_obsidian
Version: 0.3.25.2
Summary: A tool to export all you need to obsidian
License: AGPL-3.0
Author: hx
Author-email: im@bgzo.cc
Requires-Python: >=3.12
Classifier: License :: OSI Approved :: GNU Affero General Public License v3
Classifier: Programming Language :: Python :: 3
Classifier: Programming Language :: Python :: 3.12
Classifier: Programming Language :: Python :: 3.13
Requires-Dist: beautifulsoup4 (>=4.13.4,<4.14.0)
Requires-Dist: click (>=8.2.1,<8.3.0)
Requires-Dist: html2text (>=2025.4.15,<2025.5.0)
Requires-Dist: markdownify (>=1.1.0,<1.2.0)
Requires-Dist: pytest (>=8.4.1,<8.5.0)
Requires-Dist: python-frontmatter (>=1.1.0,<1.2.0)
Requires-Dist: requests (>=2.32.4,<2.33.0)
Requires-Dist: urllib3 (>=2.5.0,<2.6.0)
Project-URL: Repository, https://github.com/bGZo/playground/tree/2025/07/export-to-obsidian
